woox/__init__.py
woox/authentication.py
woox/client.py
woox/enums.py
woox/exceptions.py
woox/streams.py
woox/threaded_stream.py
python_woox-0.2.1.dist-info/LICENSE
python_woox-0.2.1.dist-info/METADATA
python_woox-0.2.1.dist-info/WHEEL
python_woox-0.2.1.dist-info/top_level.txt
python_woox-0.2.1.dist-info/zip-safe
python_woox-0.2.1.dist-info/RECORD
