Metadata-Version: 2.1
Name: python-woox
Version: 0.2.1
Summary: WooX python API
Home-page: https://github.com/wanth1997/python-wootrade
Author: tinghsuwan
Author-email: wanth1997@gmail.com
License: MIT
Classifier: Programming Language :: Python :: 3
Classifier: License :: OSI Approved :: MIT License
Classifier: Operating System :: OS Independent
License-File: LICENSE
Requires-Dist: requests
Requires-Dist: aiohttp
Requires-Dist: websockets
